README.txt
setup.py
flv2img/__init__.py
flv2img/flv2img.py
flv2img0.1.5.egg-info/PKG-INFO
flv2img0.1.5.egg-info/SOURCES.txt
flv2img0.1.5.egg-info/dependency_links.txt
flv2img0.1.5.egg-info/top_level.txt